latex_subfigs_combiner/__init__.py
latex_subfigs_combiner/combine_subfigures.py
latex_subfigs_combiner-1.0.0.dist-info/entry_points.txt
latex_subfigs_combiner-1.0.0.dist-info/LICENSE
latex_subfigs_combiner-1.0.0.dist-info/WHEEL
latex_subfigs_combiner-1.0.0.dist-info/METADATA
latex_subfigs_combiner-1.0.0.dist-info/RECORD
