Metadata-Version: 2.1
Name: latex-subfigs-combiner
Version: 1.0.0
Summary: Python script for combining LaTeX figures composed of subfigures.
Home-page: https://github.com/GiovanniBordiga/latex-subfigs-combiner
License: MIT
Keywords: latex,latex-figure,latex-subfigure,python-script
Author: Giovanni Bordiga
Author-email: gio.61192@gmail.com
Requires-Python: >=3.6,<4.0
Classifier: License :: OSI Approved :: MIT License
Classifier: Programming Language :: Python :: 3
Classifier: Programming Language :: Python :: 3.6
Classifier: Programming Language :: Python :: 3.7
Classifier: Programming Language :: Python :: 3.8
Classifier: Programming Language :: Python :: 3.9
Requires-Dist: PyPDF2 (>=1.26.0,<2.0.0)
Project-URL: Repository, https://github.com/GiovanniBordiga/latex-subfigs-combiner
